dbt_dynamic_models/__init__.py
dbt_dynamic_models/base.py
dbt_dynamic_models/cli.py
dbt_dynamic_models/params.py
dbt_dynamic_models/utils.py
dbt_dynamic_models-0.1.3.dist-info/entry_points.txt
dbt_dynamic_models-0.1.3.dist-info/WHEEL
dbt_dynamic_models-0.1.3.dist-info/METADATA
dbt_dynamic_models-0.1.3.dist-info/RECORD
