Metadata-Version: 2.1
Name: dbt-dynamic-models
Version: 0.1.3
Summary: Generate dbt models from config
License: MIT
Author: Doug Guthrie
Author-email: douglas.p.guthrie@gmail.com
Requires-Python: >=3.9,<4.0
Classifier: License :: OSI Approved :: MIT License
Classifier: Programming Language :: Python :: 3
Classifier: Programming Language :: Python :: 3.9
Classifier: Programming Language :: Python :: 3.10
Provides-Extra: bigquery
Provides-Extra: databricks
Provides-Extra: postgres
Provides-Extra: redshift
Provides-Extra: snowflake
Provides-Extra: spark
Requires-Dist: PyYAML (>=6.0,<7.0)
Requires-Dist: dbt-bigquery (>=1.0.0,<2.0.0); extra == "bigquery"
Requires-Dist: dbt-databricks (>=1.0.0,<2.0.0); extra == "databricks"
Requires-Dist: dbt-postgres (>=1.0.0,<2.0.0); extra == "postgres"
Requires-Dist: dbt-redshift (>=1.0.0,<2.0.0); extra == "redshift"
Requires-Dist: dbt-snowflake (>=1.0.0,<2.0.0); extra == "snowflake"
Requires-Dist: dbt-spark (>=1.0.0,<2.0.0); extra == "spark"
Requires-Dist: typer[all] (>=0.6.1,<0.7.0)
